start_selenium_webdriver/__init__.py
start_selenium_webdriver/webdriver_startup.py
start_selenium_webdriver-0.3.1.dist-info/LICENSE
start_selenium_webdriver-0.3.1.dist-info/METADATA
start_selenium_webdriver-0.3.1.dist-info/WHEEL
start_selenium_webdriver-0.3.1.dist-info/top_level.txt
start_selenium_webdriver-0.3.1.dist-info/RECORD
