Metadata-Version: 2.1
Name: start-selenium-webdriver
Version: 0.3.1
Summary: One simple selenium webdriver start script that (tries to) take care of binary locations and dependendencies in a platform independent manner.
Home-page: https://github.com/JoachimDunkel/start_selenium_webdriver
Author: Joachim Dunkel
Author-email: joachim.github@gmx.at
Project-URL: Bug Tracker, https://github.com/JoachimDunkel/start_selenium_webdriver/issues
Classifier: Programming Language :: Python :: 3
Classifier: License :: OSI Approved :: MIT License
Classifier: Operating System :: OS Independent
Requires-Python: >=3.6
License-File: LICENSE
Requires-Dist: selenium
Requires-Dist: webdriver-manager
